LICENSE
MANIFEST.in
README.rst
setup.cfg
setup.py
coder/__init__.py
coder/admin.py
coder/apps.py
coder/compare.py
coder/forms.py
coder/models.py
coder/tests.py
coder/urls.py
coder/views.py
coder/migrations/0001_initial.py
coder/migrations/0002_auto_20200718_0535.py
coder/migrations/0003_auto_20200718_0549.py
coder/migrations/0004_auto_20200718_0550.py
coder/migrations/0005_auto_20200718_0556.py
coder/migrations/0006_auto_20200718_1725.py
coder/migrations/0007_auto_20200718_1747.py
coder/migrations/0008_auto_20200718_2017.py
coder/migrations/0009_question_iscorrect.py
coder/migrations/0010_auto_20200721_1056.py
coder/migrations/0011_question_iscorrect.py
coder/migrations/0012_auto_20200722_2033.py
coder/migrations/__init__.py
coder/static/coder/check.svg
coder/static/coder/main.css
coder/templates/coder/base.html
coder/templates/coder/coder_detail.html
coder/templates/coder/coder_form.html
coder/templates/coder/coder_list.html
coder/templatetags/__init__.py
coder/templatetags/viewans.py
django_judge.egg-info/PKG-INFO
django_judge.egg-info/SOURCES.txt
django_judge.egg-info/dependency_links.txt
django_judge.egg-info/top_level.txt
docs/readme.md